autonity_cli/__init__.py
autonity_cli/__main__.py
autonity_cli/__version__.py
autonity_cli/abi_parser.py
autonity_cli/auth.py
autonity_cli/config.py
autonity_cli/config_file.py
autonity_cli/constants.py
autonity_cli/denominations.py
autonity_cli/device.py
autonity_cli/erc20.py
autonity_cli/keyfile.py
autonity_cli/logging.py
autonity_cli/options.py
autonity_cli/py.typed
autonity_cli/tx.py
autonity_cli/user.py
autonity_cli/utils.py
autonity_cli/commands/__init__.py
autonity_cli/commands/account.py
autonity_cli/commands/block.py
autonity_cli/commands/contract.py
autonity_cli/commands/governance.py
autonity_cli/commands/node.py
autonity_cli/commands/protocol.py
autonity_cli/commands/token.py
autonity_cli/commands/tx.py
autonity_cli/commands/validator.py
autonity_cli-2.0.2.dist-info/METADATA
autonity_cli-2.0.2.dist-info/WHEEL
autonity_cli-2.0.2.dist-info/entry_points.txt
autonity_cli-2.0.2.dist-info/licenses/LICENSE
autonity_cli-2.0.2.dist-info/RECORD
