Metadata-Version: 2.4
Name: autonity-cli
Version: 2.0.2
Summary: Command line interface to interact with Autonity
Project-URL: Homepage, https://github.com/autonity/autonity-cli
Project-URL: Source, https://github.com/autonity/autonity-cli
Project-URL: Issues, https://github.com/autonity/autonity-cli/issues
Project-URL: Changes, https://github.com/autonity/autonity-cli/blob/master/CHANGELOG.md
License-Expression: MIT
License-File: LICENSE
Keywords: autonity,cli,rpc,web3
Classifier: Development Status :: 4 - Beta
Classifier: License :: OSI Approved :: MIT License
Classifier: Programming Language :: Python
Classifier: Programming Language :: Python :: 3.9
Classifier: Programming Language :: Python :: 3.10
Classifier: Programming Language :: Python :: 3.11
Classifier: Programming Language :: Python :: 3.12
Classifier: Programming Language :: Python :: 3.13
Requires-Python: >=3.10
Requires-Dist: autonity==6.0.0
Requires-Dist: click-option-group
Requires-Dist: click>=8.1.8
Requires-Dist: trezor[ethereum]>=0.13.10
